{"precision": 0.95, "recall": 0.9827586206896551, "hmean": 0.9661016949152542, "gtWords": 58, "detWords": 60, "correct": 57.0, "log": "<br>det word = YAM found<br>det word = FRESH found<br>det word = NO.145G, found<br>det word = JALAN found<br>det word = RIMBUNAN found<br>det word = RAYA found<br>det word = 1, found<br>det word = LAMAN found<br>det word = RIMBUNAN found<br>det word = KEPONG, found<br>det word = 52100 found<br>det word = KUALA found<br>det word = LUMPUR found<br>det word = TEL: found<br>det word = (603) found<br>det word = 6243 found<br>det word = 5520 found<br>det word = GST found<br>det word = ID=001817907200 found<br>det word = INVOICE: found<br>det word = 001-9823 found<br>det word = DATE: found<br>det word = 2016-07-31 found<br>det word = 13:49:10 found<br>det word = DINE found<br>det word = IN found<br>det word = Q02 found<br>det word = OYSTER found<br>det word = MEE found<br>det word = SUA found<br>det word = :1 found<br>det word = 1 found<br>det word = RM7.50 found<br>det word = SUB-TOTAL found<br>det word = 6% found<br>det word = GST found<br>det word = GRAND found<br>det word = TOTAL found<br>det word = RM7.50 found<br>det word = RM0.45 found<br>det word = RM7.95 found<br>det word = CASH found<br>det word = CHANGE found<br>det word = RM10.05 found<br>det word = RM2.10 found<br>det word = THANK found<br>det word = YOU. found<br>det word = PLEASE found<br>det word = VISIT found<br>det word = US found<br>det word = AT not found<br>det word = : not found<br>det word = - not found<br>det word = FACEBOOK:-YAM found<br>det word = FRESH found<br>det word = 001-2016-07-31 found<br>det word = 13:49:29 found<br>det word = LIJIE found<br>det word = 001-9823 found<br>det word = [1] found"}